pyanova_nano/__init__.py
pyanova_nano/client.py
pyanova_nano/commands.py
pyanova_nano/types.py
pyanova_nano/proto/messages.proto
pyanova_nano/proto/messages_pb2.py
pyanova_nano/proto/messages_pb2.pyi
pyanova_nano/tests/__init__.py
pyanova_nano/tests/conftest.py
pyanova_nano/tests/test_client.py
pyanova_nano/tests/test_commands.py
pyanova_nano-0.3.2.dist-info/METADATA
pyanova_nano-0.3.2.dist-info/WHEEL
pyanova_nano-0.3.2.dist-info/licenses/LICENSE
pyanova_nano-0.3.2.dist-info/RECORD
