Metadata-Version: 2.4
Name: pyanova-nano
Version: 0.3.2
Summary: Python API to interact with the Anova Nano.
Project-URL: Homepage, https://github.com/filmkorn/pyanova-nano
Project-URL: Issues, https://github.com/filmkorn/pyanova-nano/issues
Author-email: Mitja Muller-Jend <mitja.muller-jend+github@gmail.com>
License-File: LICENSE
Keywords: anova,ble,bluetooth,nano,pyanova,sous-vide
Classifier: License :: OSI Approved :: Apache Software License
Classifier: Operating System :: OS Independent
Classifier: Programming Language :: Python :: 3
Requires-Python: >=3.11
Requires-Dist: bleak-retry-connector<5,>=3.5
Requires-Dist: bleak<3,>=0.19
Requires-Dist: protobuf<7,>=4
Provides-Extra: dev
Requires-Dist: black; extra == 'dev'
Requires-Dist: isort; extra == 'dev'
Provides-Extra: release
Requires-Dist: hatch; extra == 'release'
